cp2k_spm_tools/__init__.py
cp2k_spm_tools/bader_wrapper.py
cp2k_spm_tools/common.py
cp2k_spm_tools/cp2k_ftsts.py
cp2k_spm_tools/cp2k_grid_orbitals.py
cp2k_spm_tools/cp2k_overlap_matrix.py
cp2k_spm_tools/cp2k_stm_sts.py
cp2k_spm_tools/cp2k_utils.py
cp2k_spm_tools/cp2k_wfn_file.py
cp2k_spm_tools/cube.py
cp2k_spm_tools/cube_utils.py
cp2k_spm_tools/cycles.py
cp2k_spm_tools/igor.py
cp2k_spm_tools/qe_utils.py
cp2k_spm_tools/cli/__init__.py
cp2k_spm_tools/cli/bader_bond_order.py
cp2k_spm_tools/cli/crop_orbs_wfn.py
cp2k_spm_tools/cli/cube_from_wfn.py
cp2k_spm_tools/cli/cube_operations.py
cp2k_spm_tools/cli/cube_single_column.py
cp2k_spm_tools/cli/cube_split.py
cp2k_spm_tools/cli/hrstm_from_wfn.py
cp2k_spm_tools/cli/overlap_from_wfns.py
cp2k_spm_tools/cli/stm_sts_from_wfn.py
cp2k_spm_tools/cli/stm_sts_plotter.py
cp2k_spm_tools/hrstm_tools/__init__.py
cp2k_spm_tools/hrstm_tools/cp2k_grid_matrix.py
cp2k_spm_tools/hrstm_tools/hrstm.py
cp2k_spm_tools/hrstm_tools/hrstm_utils.py
cp2k_spm_tools/hrstm_tools/interpolator.py
cp2k_spm_tools/hrstm_tools/ppstm_grid_orbitals.py
cp2k_spm_tools/hrstm_tools/tip_coeffs.py
cp2k_spm_tools-1.5.0.dist-info/LICENSE
cp2k_spm_tools-1.5.0.dist-info/METADATA
cp2k_spm_tools-1.5.0.dist-info/WHEEL
cp2k_spm_tools-1.5.0.dist-info/entry_points.txt
cp2k_spm_tools-1.5.0.dist-info/top_level.txt
cp2k_spm_tools-1.5.0.dist-info/RECORD
