Metadata-Version: 2.2
Name: cp2k-spm-tools
Version: 1.5.0
Summary: CP2K Scanning Probe Microscopy tools.
Author-email: Kristjan Eimre <kristjaneimre@gmail.com>, Edoardo Baldi <edoardo.baldi@empa.ch>
License: MIT License
Project-URL: Homepage, https://github.com/nanotech-empa/cp2k-spm-tools
Project-URL: Bug Tracker, https://github.com/nanotech-empa/cp2k-spm-tools/issues
Classifier: Programming Language :: Python :: 3
Classifier: License :: OSI Approved :: MIT License
Classifier: Operating System :: OS Independent
Requires-Python: >=3.8
License-File: LICENSE
Requires-Dist: numpy<2,>=1.22
Requires-Dist: scipy<2,>=1.10
Requires-Dist: ase<4,>=3.15
Requires-Dist: matplotlib<4,>=3.0
Requires-Dist: mpi4py>3.1
Provides-Extra: dev
Requires-Dist: ruff; extra == "dev"
Requires-Dist: pre-commit; extra == "dev"
Requires-Dist: bumpver>=2023.1129; extra == "dev"
